textcase/__init__.py
textcase/py.typed
textcase-0.4.5.dist-info/METADATA
textcase-0.4.5.dist-info/WHEEL
textcase-0.4.5.dist-info/licenses/LICENSE.md
textcase-0.4.5.dist-info/RECORD
