Metadata-Version: 2.4
Name: textcase
Version: 0.4.5
Summary: Python library for text case conversions.
Project-URL: Homepage, https://zobweyt.github.io/textcase
Project-URL: Documentation, https://zobweyt.github.io/textcase
Project-URL: Repository, https://github.com/zobweyt/textcase
Project-URL: Issues, https://github.com/zobweyt/textcase/issues
Project-URL: Changelog, https://github.com/zobweyt/textcase/blob/main/CHANGELOG.md
Author-email: Nikita Gaziev <zobweyt@gmail.com>
Maintainer-email: Nikita Gaziev <zobweyt@gmail.com>
License-Expression: MIT
License-File: LICENSE.md
Keywords: camel-case,case,constant-case,conversion,kebab-case,lower-case,middot-case,pascal-case,sentence-case,snake-case,text,title-case,upper-case
Classifier: Development Status :: 4 - Beta
Classifier: Intended Audience :: Developers
Classifier: License :: OSI Approved :: MIT License
Classifier: Natural Language :: English
Classifier: Natural Language :: Russian
Classifier: Operating System :: OS Independent
Classifier: Programming Language :: Python
Classifier: Programming Language :: Python :: 3
Classifier: Programming Language :: Python :: 3 :: Only
Classifier: Programming Language :: Python :: 3.9
Classifier: Programming Language :: Python :: 3.10
Classifier: Programming Language :: Python :: 3.11
Classifier: Programming Language :: Python :: 3.12
Classifier: Programming Language :: Python :: 3.13
Classifier: Programming Language :: Python :: 3.14
Classifier: Topic :: Software Development
Classifier: Topic :: Software Development :: Libraries
Classifier: Topic :: Software Development :: Libraries :: Python Modules
Classifier: Topic :: Text Processing
Classifier: Topic :: Text Processing :: Linguistic
Classifier: Typing :: Typed
Requires-Python: >=3.9
